{
	"pid": 41540,
	"date": "2025-10-31T10:52:51.489Z",
	"port": 3000,
	"ip": "0.0.0.0",
	"stats": [
		{
			"id": null,
			"version": {
				"node": "v22.14.0",
				"total": "4",
				"build": 4099,
				"app": "1.0.0"
			},
			"pid": 41540,
			"thread": "",
			"mode": "release",
			"overload": 0,
			"date": "2025-10-31T10:56:51.586Z",
			"memory": 9.68,
			"rm": 0,
			"fm": 0,
			"wm": 0,
			"em": 0,
			"mm": 0,
			"om": 0,
			"dm": 0,
			"um": 0,
			"pm": 0,
			"sm": 0,
			"cm": 0,
			"dbrm": 0,
			"dbwm": 0,
			"usage": 6,
			"requests": 4,
			"pending": 0,
			"external": 0,
			"errors": 0,
			"timeouts": 0,
			"online": 0,
			"uptime": 5,
			"download": 0,
			"upload": 0.016,
			"status": []
		}
	]
}